[{"link":"https:\/\/drive.google.com\/file\/d\/1rDdZjYH6B4DQArkPmlO1GCEss3QxjArw\/preview","book":"Book 1 Water","eps":"Episode 01","judul":"The Boy in the Iceberg","date":"21 Februari 2005","id_eps":0},{"link":"https:\/\/drive.google.com\/file\/d\/1oIQYgDN9vsCRgmx0TRIeDYsHD04eBjdZ\/preview","book":"Book 1 Water","eps":"Episode 02","judul":"The Avatar Returns","date":"21 Februari 2005","id_eps":1},{"link":"https:\/\/drive.google.com\/file\/d\/1E4Eu_OP-_7i18m38mAF4uEpaHfkIbOEQ\/preview","book":"Book 1 Water","eps":"Episode 03","judul":"The Southern Air Temple","date":"25 Februari 2005","id_eps":2},{"link":"https:\/\/drive.google.com\/file\/d\/1K91oC7UnGp-bqCnXeNKO0zQ2E3Kw6419\/preview","book":"Book 1 Water","eps":"Episode 04","judul":"The Warriors of Kyoshi","date":"4 Maret 2005","id_eps":3},{"link":"https:\/\/drive.google.com\/file\/d\/1EMxBDtbJWeElkYYGPBScdo9dK_bZrbPd\/preview","book":"Book 1 Water","eps":"Episode 05","judul":"The King of Omashu","date":"18 Maret 2005","id_eps":4},{"link":"https:\/\/drive.google.com\/file\/d\/1AcbHJBSa43K8vBTj47EkA0uSFTdpssDs\/preview","book":"Book 1 Water","eps":"Episode 06","judul":"Imprisoned","date":"25 Maret 2005","id_eps":5},{"link":"https:\/\/drive.google.com\/file\/d\/1OY_tpDY3KJ2KL1pytmKc8-39oU6EqNJh\/preview","book":"Book 1 Water","eps":"Episode 07","judul":"Winter Solstice","date":" Part 1: The Spirit World","id_eps":6},{"link":"https:\/\/drive.google.com\/file\/d\/1cQKuaJbWRzbtwsWHX_7LV9_7MkB8Oj_E\/preview","book":"Book 1 Water","eps":"Episode 08","judul":"Winter Solstice","date":" Part 2: Avatar Roku","id_eps":7},{"link":"https:\/\/drive.google.com\/file\/d\/197dNt7hDD1cTjJy034FwtWn6L_yHNEjh\/preview","book":"Book 1 Water","eps":"Episode 09","judul":"The Waterbending Scroll","date":"28 April 2005","id_eps":8},{"link":"https:\/\/drive.google.com\/file\/d\/14-XUyYe1BOvcTOHDVCED94gYuPJvTzOi\/preview","book":"Book 1 Water","eps":"Episode 10","judul":"Jet","date":"6 Mei 2005","id_eps":9},{"link":"https:\/\/drive.google.com\/file\/d\/16i477A07fGkDBfx-Rf73VtV8hJSWVqsk\/preview","book":"Book 1 Water","eps":"Episode 11","judul":"The Great Divide","date":"20 Mei 2005","id_eps":10},{"link":"https:\/\/drive.google.com\/file\/d\/11dmlO_Xk8iMn1SgluNa8Sc0lNZo21mYD\/preview","book":"Book 1 Water","eps":"Episode 12","judul":"The Storm","date":"3 Juni 2005","id_eps":11},{"link":"https:\/\/drive.google.com\/file\/d\/1LgutNpGElpIz7BZvOxsoCaVrZyWvVV9q\/preview","book":"Book 1 Water","eps":"Episode 13","judul":"The Blue Spirit","date":"17 Juni 2005","id_eps":12},{"link":"https:\/\/drive.google.com\/file\/d\/1_tTlsZ7cuNTfbTorHG2m_YAGgAcFnGIU\/preview","book":"Book 1 Water","eps":"Episode 14","judul":"The Fortuneteller","date":"23 September 2005","id_eps":13},{"link":"https:\/\/drive.google.com\/file\/d\/1NEo_1QipCtxJC_Duk77BWberzv3_KFvo\/preview","book":"Book 1 Water","eps":"Episode 15","judul":"Bato of the Water Tribe","date":"7 Oktober 2005","id_eps":14},{"link":"https:\/\/drive.google.com\/file\/d\/17hq8s_5yhhG7ixze4hKzReNpyfPF7S2i\/preview","book":"Book 1 Water","eps":"Episode 16","judul":"The Deserter","date":"21 Oktober 2005","id_eps":15},{"link":"https:\/\/drive.google.com\/file\/d\/1i8VFet7Dgcjds5rtdAl7go4yC2tUaFYG\/preview","book":"Book 1 Water","eps":"Episode 17","judul":"The Northern Air Temple","date":"4 November 2005","id_eps":16},{"link":"https:\/\/drive.google.com\/file\/d\/19Ex0pd5nJolWfMgvyPhGgfWzcUisO2QI\/preview","book":"Book 1 Water","eps":"Episode 18","judul":"The Waterbending Master","date":"18 November 2005","id_eps":17},{"link":"https:\/\/drive.google.com\/file\/d\/1KE0sovHzLvNLIjJq9T0qPOMJ6eu7f2Gk\/preview","book":"Book 1 Water","eps":"Episode 19","judul":"The Siege of the North Part 1","date":"2 Desember 2005","id_eps":18},{"link":"https:\/\/drive.google.com\/file\/d\/1RAi4HbWPKs_gcuKKmwO-dDbVHMinLhbR\/preview","book":"Book 1 Water","eps":"Episode 20","judul":"The Siege of the North Part 2","date":"2 Desember 2005","id_eps":19},{"link":"https:\/\/drive.google.com\/file\/d\/1xyGpEJNQyrD_H3bPoB4N_izYQCojlaCC\/preview","book":"Book 2 Earth","eps":"Episode 01","judul":"The Avatar State","date":"17 Maret 2006","id_eps":20},{"link":"https:\/\/drive.google.com\/file\/d\/13dHKVNSSo2qlDUSBCMV0JKKe_1F2SZHi\/preview","book":"Book 2 Earth","eps":"Episode 02","judul":"The Cave of Two Lovers","date":"24 Maret 2006","id_eps":21},{"link":"https:\/\/drive.google.com\/file\/d\/1gfPZzX16yOtvux7jIlW3Lk9Dy2nhzF1D\/preview","book":"Book 2 Earth","eps":"Episode 03","judul":"Return to Omashu","date":"7 April 2006","id_eps":22},{"link":"https:\/\/drive.google.com\/file\/d\/1rs-E3jywwDpLkI3qLpQvtO8EwmUqZGWM\/preview","book":"Book 2 Earth","eps":"Episode 04","judul":"The Swamp","date":"14 April 2006","id_eps":23},{"link":"https:\/\/drive.google.com\/file\/d\/109iDkZ_JHaO7Ft2jr3TTirxtxfCmo263\/preview","book":"Book 2 Earth","eps":"Episode 05","judul":"Avatar Day","date":"28 April 2006","id_eps":24},{"link":"https:\/\/drive.google.com\/file\/d\/1NEeKgYcZ9Z384pr9ZiP-LTHPdTKAGqtd\/preview","book":"Book 2 Earth","eps":"Episode 06","judul":"The Blind Bandit","date":"5 Mei 2006","id_eps":25},{"link":"https:\/\/drive.google.com\/file\/d\/1rOJ4VZ9qe1pSGFJdz6a0hcCgzgXYGTew\/preview","book":"Book 2 Earth","eps":"Episode 07","judul":"Zuko Alone","date":"12 Mei 2006","id_eps":26},{"link":"https:\/\/drive.google.com\/file\/d\/1BP2isdtzSxViXWQhgSrmFTUco1gJh8T5\/preview","book":"Book 2 Earth","eps":"Episode 08","judul":"The Chase","date":"26 Mei 2006","id_eps":27},{"link":"https:\/\/drive.google.com\/file\/d\/12eXTm0BmD9xoMxZwH1fhb-vMmBqP3QvA\/preview","book":"Book 2 Earth","eps":"Episode 09","judul":"Bitter Work","date":"2 Juni 2006","id_eps":28},{"link":"https:\/\/drive.google.com\/file\/d\/1W5EvJMmqQPcv93VGHo9PMyILYpkXlK2r\/preview","book":"Book 2 Earth","eps":"Episode 10","judul":"The Library","date":"14 Juli 2006","id_eps":29},{"link":"https:\/\/drive.google.com\/file\/d\/1q-d_09nJLC-upcSOJWtHSW90RxQb2ncv\/preview","book":"Book 2 Earth","eps":"Episode 11","judul":"The Desert","date":"14 Juli 2006","id_eps":30},{"link":"https:\/\/drive.google.com\/file\/d\/1HYIQWr3dlD97FAaDpPVWThlu1G-WDFhp\/preview","book":"Book 2 Earth","eps":"Episode 12","judul":"The Serpent's Pass","date":"15 September 2006","id_eps":31},{"link":"https:\/\/drive.google.com\/file\/d\/17yXJQ4hhHZSuzj1_YQuA2w365CsovGVA\/preview","book":"Book 2 Earth","eps":"Episode 13","judul":"The Drill","date":"15 September 2006","id_eps":32},{"link":"https:\/\/drive.google.com\/file\/d\/1pvg1o2N0R56qdRqGmjgZ_XMqcBSn3mT0\/preview","book":"Book 2 Earth","eps":"Episode 14","judul":"City of Walls and Secrets","date":"22 September 2006","id_eps":33},{"link":"https:\/\/drive.google.com\/file\/d\/1SjaxhEmwk22sAy5xPujlOFjqf8yUiTW6\/preview","book":"Book 2 Earth","eps":"Episode 15","judul":"Tales of Ba Sing Se","date":"29 September 2006","id_eps":34},{"link":"https:\/\/drive.google.com\/file\/d\/1ZnaT9lMQzz50wUEZtg3E0obGLlZHNGeB\/preview","book":"Book 2 Earth","eps":"Episode 16","judul":"Appa's Lost Days","date":"12 Oktober 2006","id_eps":35},{"link":"https:\/\/drive.google.com\/file\/d\/1g2U35KCsu04-1HGpZ1qCDq7qKgXsTKIi\/preview","book":"Book 2 Earth","eps":"Episode 17","judul":"Lake Laogai","date":"3 November 2006","id_eps":36},{"link":"https:\/\/drive.google.com\/file\/d\/15ttYtp891hEomWq9TrcfDKbYDGD-8CRs\/preview","book":"Book 2 Earth","eps":"Episode 18","judul":"The Earth King","date":"16 November 2006","id_eps":37},{"link":"https:\/\/drive.google.com\/file\/d\/1ndEthqWRVzMV87-4bPORlx8OPhfAfoL1\/preview","book":"Book 2 Earth","eps":"Episode 19","judul":"The Guru","date":"1 Desember 2006","id_eps":38},{"link":"https:\/\/drive.google.com\/file\/d\/1ohoMdW_7OQgEWO25Emm7S_KBJkAmKOR-\/preview","book":"Book 2 Earth","eps":"Episode 20","judul":"The Crossroads of Destiny","date":"1 Desember 2006","id_eps":39},{"link":"https:\/\/drive.google.com\/file\/d\/11FQ9jm0MC525bQTveOzzj8KVxHFfSG8a\/preview","book":"Book 3 Fire","eps":"Episode 01","judul":"The Awakening","date":"21 September 2007","id_eps":40},{"link":"https:\/\/drive.google.com\/file\/d\/1b9ozxm54qRlpkPid8cJ1OmEXmEi8iB6k\/preview","book":"Book 3 Fire","eps":"Episode 02","judul":"The Headband","date":"28 September 2007","id_eps":41},{"link":"https:\/\/drive.google.com\/file\/d\/14iChpu6tZFKB2NNYyRC498SjJPHC4JYW\/preview","book":"Book 3 Fire","eps":"Episode 03","judul":"The Painted Lady","date":"5 Oktober 2007","id_eps":42},{"link":"https:\/\/drive.google.com\/file\/d\/17-LPI_7gMB9DAMReOdILuLImGFlQao6b\/preview","book":"Book 3 Fire","eps":"Episode 04","judul":"Sokka's Master","date":"12 Oktober 2007","id_eps":43},{"link":"https:\/\/drive.google.com\/file\/d\/1X6hwPHNso-pJpp0wfQnkvLdQ5qZCx5zH\/preview","book":"Book 3 Fire","eps":"Episode 05","judul":"The Beach","date":"19 Oktober 2007","id_eps":44},{"link":"https:\/\/drive.google.com\/file\/d\/1A5sgOuClSZKbv4lUwTjOEWFoj_elhrpC\/preview","book":"Book 3 Fire","eps":"Episode 06","judul":"The Avatar and the Firelord","date":"26 Oktober 2007","id_eps":45},{"link":"https:\/\/drive.google.com\/file\/d\/1FbSo-LW9-HCfkZCLOu3-6DlaU77WZvm3\/preview","book":"Book 3 Fire","eps":"Episode 07","judul":"The Runaway","date":"2 November 2007","id_eps":46},{"link":"https:\/\/drive.google.com\/file\/d\/1NwRXOR8E96YBaCvfPYuXe5G-ejx-TZj6\/preview","book":"Book 3 Fire","eps":"Episode 08","judul":"The Puppetmaster","date":"9 November 2007","id_eps":47},{"link":"https:\/\/drive.google.com\/file\/d\/1AF2qCgo5GskF22kbFUqYe5aKUetF4lV2\/preview","book":"Book 3 Fire","eps":"Episode 09","judul":"Nightmares and Daydreams","date":"16 November 2007","id_eps":48},{"link":"https:\/\/drive.google.com\/file\/d\/14-Nhb9VIVbX0PsPgz6NjFGMIiFkgcAvc\/preview","book":"Book 3 Fire","eps":"Episode 10","judul":"The Day of Black Sun Part 1: The Invasion","date":"30 November 2007","id_eps":49},{"link":"https:\/\/drive.google.com\/file\/d\/12yzJlKErVl_i1Xrlu0GwWB4MtWGOYXu0\/preview","book":"Book 3 Fire","eps":"Episode 11","judul":"The Day of Black Sun Part 2: The Eclipse","date":"30 November 2007","id_eps":50},{"link":"https:\/\/drive.google.com\/file\/d\/1ThXVC5LijcOhyXNKu2F5sC-ZhkrAM09t\/preview","book":"Book 3 Fire","eps":"Episode 12","judul":"The Western Air Temple","date":"14 Juli 2008","id_eps":51},{"link":"https:\/\/drive.google.com\/file\/d\/1wcFaDmSAfQ7yvaaDgiciX9G2mucpe9xA\/preview","book":"Book 3 Fire","eps":"Episode 13","judul":"The Firebending Masters","date":"15 Juli 2008","id_eps":52},{"link":"https:\/\/drive.google.com\/file\/d\/1r9xyDGe9fRx2-ZWJAyIwwd-NoQLlSOgd\/preview","book":"Book 3 Fire","eps":"Episode 14","judul":"The Boiling Rock Part 1","date":"16 Juli 2008","id_eps":53},{"link":"https:\/\/drive.google.com\/file\/d\/1cU4d3QPhrDWSchAPuoUnZXY2IpTN7yBY\/preview","book":"Book 3 Fire","eps":"Episode 15","judul":"The Boiling Rock Part 2","date":"16 Juli 2008","id_eps":54},{"link":"https:\/\/drive.google.com\/file\/d\/1OPRl2JJwhR3OvB0uXs5IUAHk6kk-JFSB\/preview","book":"Book 3 Fire","eps":"Episode 16","judul":"The Southern Raiders","date":"17 Juli 2008","id_eps":55},{"link":"https:\/\/drive.google.com\/file\/d\/1-I7smPq3wIg5bpngarGC40_mgQ-rNrOW\/preview","book":"Book 3 Fire","eps":"Episode 17","judul":"The Ember Island Players","date":"18 Juli 2008","id_eps":56},{"link":"https:\/\/drive.google.com\/file\/d\/1GQDj_cllzDuYi760xZK_NDuz5Aana1YO\/preview","book":"Book 3 Fire","eps":"Episode 18","judul":"Komet Sozin Bagian 1: The Phoenix King","date":"19 Juli 2008","id_eps":57},{"link":"https:\/\/drive.google.com\/file\/d\/1UDXOr_3Z97uvgIl5De7jAMxb_o1fZyKf\/preview","book":"Book 3 Fire","eps":"Episode 19","judul":"Komet Sozin Bagian 2: The Old Masters","date":"19 Juli 2008","id_eps":58},{"link":"https:\/\/drive.google.com\/file\/d\/1V-Yz6IFkm65ZJL865nTGekIYfL_g14A_\/preview","book":"Book 3 Fire","eps":"Episode 20","judul":"Komet Sozin Bagian 3: Into the Inferno","date":"19 Juli 2008","id_eps":59},{"link":"https:\/\/drive.google.com\/file\/d\/1nKyJIC5qJUkOMN-YbJ0tp-q_ORJrLGh-\/preview","book":"Book 3 Fire","eps":"Episode 21","judul":"Komet Sozin Bagian 4: Avatar Aang","date":"19 Juli 2008","id_eps":60}]